{"ref": {"full": "Seddon, K. R.; Stark, A.; Torres, M.-J. (2002) ACS Symp. Ser. 819, 34-49.", "title": "Viscosity and Density of 1-Alkyl-3-methylimidazolium Ionic Liquids"}, "title": "Transport properties: Viscosity", "footer": "", "expmeth": "Cone and plate viscometry", "solvent": null, "constr": [], "components": [{"mw": "396.40", "formula": "C<SUB>16</SUB>H<SUB>31</SUB>F<SUB>6</SUB>N<SUB>2</SUB>P", "idout": "ABYMWw", "sample": [["Source:", "synthesized by the authors"], ["Purity analysis:", "dried by vacuum heating"]], "name": "1-dodecyl-3-methylimidazolium hexafluorophosphate"}], "data": [[["333.15"], ["101.325"], ["0.214", "0.065"]], [["343.15"], ["101.325"], ["0.128", "0.025"]], [["353.15"], ["101.325"], ["0.0804", "0.0083"]], [["363.15"], ["101.325"], ["0.051", "0.0014"]]], "phases": ["Liquid"], "dhead": [["Temperature, K", null], ["Pressure, kPa", null], ["Viscosity, Pa&#8226;s", "Liquid"]]}