{"components": [{"formula": "C<SUB>21</SUB>H<SUB>37</SUB>F<SUB>6</SUB>N<SUB>3</SUB>O<SUB>4</SUB>S<SUB>2</SUB>", "name": "1,3-dioctyl-1H-imidazol-3-ium bis((trifluoromethyl)sulfonyl)amide", "sample": [["Source:", "commercial source"], ["Purification:", "NMR (proton)"], ["Purity:", "99 mass %(dried by vacuum heating)"]], "idout": "ACGQMz", "mw": "573.65"}], "constr": [], "data": [[["278.15"], ["101.325"], ["0.576", "0.021"]], [["283.15"], ["101.325"], ["0.405", "0.013"]], [["288.15"], ["101.325"], ["0.2921", "0.0088"]], [["293.15"], ["101.325"], ["0.2121", "0.0058"]], [["298.15"], ["101.325"], ["0.1618", "0.0041"]], [["303.15"], ["101.325"], ["0.1239", "0.0029"]], [["308.15"], ["101.325"], ["0.0965", "0.0022"]], [["313.15"], ["101.325"], ["0.076", "0.0016"]], [["318.15"], ["101.325"], ["0.0613", "0.0013"]], [["323.15"], ["101.325"], ["0.0499", "0.001"]], [["328.15"], ["101.325"], ["0.04108", "0.00086"]], [["333.15"], ["101.325"], ["0.03446", "0.00072"]], [["338.15"], ["101.325"], ["0.02884", "0.0006"]], [["343.15"], ["101.325"], ["0.02453", "0.00051"]], [["348.15"], ["101.325"], ["0.02106", "0.00044"]], [["358.15"], ["101.325"], ["0.01588", "0.00033"]], [["363.15"], ["101.325"], ["0.01394", "0.00029"]]], "dhead": [["Temperature, K", null], ["Pressure, kPa", null], ["Viscosity, Pa&#8226;s", "Liquid"]], "phases": ["Liquid"], "ref": {"full": "Rocha, M. A. A.; Neves, C. M. S. S.; Freire, M. G.; Russina, O.; Triolo, A.; Coutinho, J. A. P.; Santos, L. M. N. B. F. (2013) J. Phys. Chem. 117, 10889-10897.", "title": "Alkylimidazolium Based Ionic Liquids: Impact of Cation Symmetry on Their Nanoscale Structural Organization"}, "title": "Transport properties: Viscosity", "solvent": null, "expmeth": "Concentric cylinders viscometry", "footer": ""}