{"ref": {"full": "Tariq, M.; Carvalho, P.; Coutinho, J. A. P.; Marrucho, I. M.; Lopes, J. N. C.; Rebelo, L. P. N. (2011) Fluid Phase Equilib. 301(1), 22-32.", "title": "Viscosity of (C2-C14) 1-alkyl-3-methylimidazolium  bis(trifluoromethylsulfonyl)amide ionic liquids in an extended temperature range"}, "title": "Transport properties: Viscosity", "expmeth": "Concentric cylinders viscometry", "solvent": null, "footer": "", "data": [[["278"], ["101.325"], ["0.403", "0.023"]], [["283"], ["101.325"], ["0.288", "0.016"]], [["288"], ["101.325"], ["0.211", "0.011"]], [["293"], ["101.325"], ["0.1575", "0.0082"]], [["298"], ["101.325"], ["0.1202", "0.0062"]], [["303"], ["101.325"], ["0.0935", "0.0047"]], [["308"], ["101.325"], ["0.0739", "0.0037"]], [["313"], ["101.325"], ["0.0594", "0.003"]], [["318"], ["101.325"], ["0.0484", "0.0024"]], [["323"], ["101.325"], ["0.0399", "0.002"]], [["328"], ["101.325"], ["0.0333", "0.0017"]], [["333"], ["101.325"], ["0.0281", "0.0014"]], [["338"], ["101.325"], ["0.024", "0.0012"]], [["343"], ["101.325"], ["0.0206", "0.001"]], [["348"], ["101.325"], ["0.01788", "0.0009"]], [["353"], ["101.325"], ["0.01563", "0.00079"]], [["358"], ["101.325"], ["0.01375", "0.00069"]]], "dhead": [["Temperature, K", null], ["Pressure, kPa", null], ["Viscosity, Pa&#8226;s", "Liquid"]], "phases": ["Liquid"], "components": [{"idout": "ABsrxx", "sample": [["Source:", "commercial source"], ["Initial purification:", "stated by supplier"], ["Initial purity:", "99 mass %"], ["Final purification:", "Karl Fischer titration;ion-selective electrode"], ["Final purity:", "0.007 water mass %;0.002 halide impurity mass %(dried by vacuum heating)"]], "name": "1-decyl-3-methylimidazolium bis(trifluoromethylsulfonyl)amide", "formula": "C<SUB>16</SUB>H<SUB>27</SUB>F<SUB>6</SUB>N<SUB>3</SUB>O<SUB>4</SUB>S<SUB>2</SUB>", "mw": "503.52"}], "constr": []}