{"footer": "", "expmeth": "Concentric cylinders viscometry", "solvent": null, "ref": {"full": "Ziyada, A. K.; Wilfred, C. D. (2014) J. Chem. Eng. Data 59(5), 1385-1390.", "title": "Effect of Temperature and Anion on Densities, Viscosities, and Refractive Indices of 1-Octyl-3-propanenitrile Imidazolium-Based Ionic Liquids"}, "title": "Transport properties: Viscosity", "constr": [], "components": [{"formula": "C<SUB>21</SUB>H<SUB>29</SUB>N<SUB>3</SUB>O<SUB>5</SUB>S", "name": "3-(2-cyanoethyl)-1-octyl-1H-imidazol-3-ium 3-sulfobenzoate", "sample": [["Source:", "synthesized by the authors"], ["Purification:", "estimated by the compiler;Karl Fischer titration;ion chromatography"], ["Purity:", "98 % (basis not specified);0.0145 water mass %;0.0059 halide impurity mass %(dried in a desiccator;dried by vacuum heating)"]], "idout": "ABfnvW", "mw": "435.54"}], "phases": ["Liquid"], "dhead": [["Temperature, K", null], ["Pressure, kPa", null], ["Viscosity, Pa&#8226;s", "Liquid"]], "data": [[["293.15"], ["101.325"], ["23.6", "3.9"]], [["298.15"], ["101.325"], ["14.4", "2.2"]], [["303.15"], ["101.325"], ["9.3", "1.3"]], [["308.15"], ["101.325"], ["5.821", "0.76"]], [["313.15"], ["101.325"], ["3.685", "0.43"]], [["318.15"], ["101.325"], ["2.405", "0.26"]], [["323.15"], ["101.325"], ["1.525", "0.14"]], [["328.15"], ["101.325"], ["1.0656", "0.09"]], [["333.15"], ["101.325"], ["0.702", "0.052"]], [["338.15"], ["101.325"], ["0.455", "0.029"]], [["343.15"], ["101.325"], ["0.299", "0.016"]], [["348.15"], ["101.325"], ["0.1882", "0.0079"]], [["353.15"], ["101.325"], ["0.1214", "0.0041"]]]}