{"constr": [], "components": [{"name": "1-(2-methoxyethyl)-1-methylpyrrolidinium bis((trifluoromethyl)sulfonyl)amide", "sample": [["Source:", "commercial source"], ["Initial purification:", "stated by supplier"], ["Initial purity:", "98 mass %"], ["Final purification:", "Karl Fischer titration"], ["Final purity:", "0.0028 water mass %(dried by vacuum heating)"]], "idout": "ABdfXI", "formula": "C<SUB>10</SUB>H<SUB>18</SUB>F<SUB>6</SUB>N<SUB>2</SUB>O<SUB>5</SUB>S<SUB>2</SUB>", "mw": "424.37"}], "phases": ["Liquid"], "dhead": [["Temperature, K", null], ["Pressure, kPa", null], ["Viscosity, Pa&#8226;s", "Liquid"]], "data": [[["258.15"], ["101.325"], ["0.62", "0.025"]], [["263.15"], ["101.325"], ["0.412", "0.016"]], [["268.15"], ["101.325"], ["0.2864", "0.0098"]], [["273.15"], ["101.325"], ["0.2046", "0.0064"]], [["278.15"], ["101.325"], ["0.1499", "0.0043"]], [["283.15"], ["101.325"], ["0.113", "0.003"]], [["288.15"], ["101.325"], ["0.0871", "0.0022"]], [["293.15"], ["101.325"], ["0.0686", "0.0017"]], [["298.15"], ["101.325"], ["0.0551", "0.0013"]], [["303.15"], ["101.325"], ["0.0449", "0.0011"]], [["308.15"], ["101.325"], ["0.03715", "0.00088"]], [["313.15"], ["101.325"], ["0.03115", "0.00073"]], [["318.15"], ["101.325"], ["0.02643", "0.00062"]], [["323.15"], ["101.325"], ["0.02266", "0.00053"]], [["328.15"], ["101.325"], ["0.01959", "0.00046"]], [["333.15"], ["101.325"], ["0.01709", "0.0004"]], [["338.15"], ["101.325"], ["0.01503", "0.00035"]], [["343.15"], ["101.325"], ["0.01332", "0.00031"]], [["348.15"], ["101.325"], ["0.01188", "0.00027"]], [["353.15"], ["101.325"], ["0.01066", "0.00024"]], [["358.15"], ["101.325"], ["0.00962", "0.00022"]], [["363.15"], ["101.325"], ["0.00872", "0.0002"]], [["368.15"], ["101.325"], ["0.00794", "0.00018"]], [["373.15"], ["101.325"], ["0.00726", "0.00017"]]], "footer": "", "expmeth": "Concentric cylinders viscometry", "solvent": null, "ref": {"title": "Influence of Molecular Structure on Densities and Viscosities of Several Ionic Liquids", "full": "Gacino, F. M.; Regueira, T.; Lugo, L.; Comunas, M. J. P.; Fernandez, J. (2011) J. Chem. Eng. Data 56(12), 4984-4999."}, "title": "Transport properties: Viscosity"}