{"constr": [], "components": [{"name": "1-butylpyridinium tetrafluoroborate", "sample": [["Source:", "commercial source"], ["Initial purification:", "stated by supplier"], ["Initial purity:", "99.0 mass %"], ["Final purification:", "Karl Fischer titration"], ["Final purity:", "0.0370 water mass %"]], "idout": "AAquhL", "formula": "C<SUB>9</SUB>H<SUB>14</SUB>BF<SUB>4</SUB>N", "mw": "223.02"}], "data": [[["288"], ["101.325"], ["0.3518", "0.0097"]], [["293"], ["101.325"], ["0.2507", "0.0059"]], [["298"], ["101.325"], ["0.1807", "0.0035"]], [["303"], ["101.325"], ["0.1316", "0.002"]], [["308"], ["101.325"], ["0.0969", "0.0012"]], [["313"], ["101.325"], ["0.072", "0.00071"]], [["318"], ["101.325"], ["0.05402", "0.00047"]], [["323"], ["101.325"], ["0.04089", "0.00037"]], [["328"], ["101.325"], ["0.03121", "0.00029"]]], "dhead": [["Temperature, K", null], ["Pressure, kPa", null], ["Viscosity, Pa&#8226;s", "Liquid"]], "phases": ["Liquid"], "title": "Transport properties: Viscosity", "ref": {"title": "Thermodynamic Behavior of the Binaries 1-Butylpyridinium Tetrafluoroborate with Water and Alkanols: Their Interpretation Using 1H NMR Spectroscopy and Quantum-Chemistry Calculations", "full": "Vreekamp, R.; Castellano, D.; Palomar, J.; Ortega, J.; Espiau, F.; Fernandez, L.; Penco, E. (2011) J. Phys. Chem. B 115, 8763-8774."}, "expmeth": "Concentric cylinders viscometry", "solvent": null, "footer": ""}