{"title": "Transport properties: Viscosity", "ref": {"title": "Phase transition and decomposition temperatures, heat capacities and viscosities of pyridinium ionic liquids", "full": "Crosthwaite, J. M.; Muldoon, M. J.; Dixon, J. K.; Anderson, J. L.; Brennecke, J. F. (2005) J. Chem. Thermodyn. 37(6), 559-568."}, "footer": "", "solvent": null, "expmeth": "Cone and plate viscometry", "constr": [], "components": [{"name": "1-hexyl-3,5-dimethylpyridinium bis(trifluoromethylsulfonyl)imide", "idout": "ABmsPm", "sample": [["Source:", "synthesized by the authors"], ["Purification:", "Karl Fischer titration"], ["Purity:", "0.003 water mass %(dried by vacuum heating)"]], "formula": "C<SUB>15</SUB>H<SUB>22</SUB>F<SUB>6</SUB>N<SUB>2</SUB>O<SUB>4</SUB>S<SUB>2</SUB>", "mw": "472.46"}], "data": [[["283"], ["101.325"], ["0.251", "0.02"]], [["293"], ["101.325"], ["0.136", "0.01"]], [["298"], ["101.325"], ["0.104", "0.006"]], [["303"], ["101.325"], ["0.081", "0.004"]], [["313"], ["101.325"], ["0.052", "0.003"]], [["323"], ["101.325"], ["0.035", "0.002"]], [["333"], ["101.325"], ["0.024", "0.001"]], [["343"], ["101.325"], ["0.018", "0.001"]]], "phases": ["Liquid"], "dhead": [["Temperature, K", null], ["Pressure, kPa", null], ["Viscosity, Pa&#8226;s", "Liquid"]]}