{"data": [[["293.15"], ["101.325"], ["0.144", "0.015"]], [["298.15"], ["101.325"], ["0.0957", "0.0097"]], [["303.15"], ["101.325"], ["0.072", "0.0072"]], [["308.15"], ["101.325"], ["0.0569", "0.0057"]], [["313.15"], ["101.325"], ["0.0458", "0.0046"]], [["318.15"], ["101.325"], ["0.0374", "0.0037"]], [["323.15"], ["101.325"], ["0.0295", "0.003"]]], "dhead": [["Temperature, K", null], ["Pressure, kPa", null], ["Viscosity, Pa&#8226;s", "Liquid"]], "phases": ["Liquid"], "components": [{"mw": "430.38", "formula": "C<SUB>12</SUB>H<SUB>16</SUB>F<SUB>6</SUB>N<SUB>2</SUB>O<SUB>4</SUB>S<SUB>2</SUB>", "idout": "ABenDA", "sample": [["Source:", "commercial source"], ["Initial purification:", "stated by supplier"], ["Initial purity:", "99 mass %"], ["Final purification:", "Karl Fischer titration"], ["Final purity:", "0.0076 water mass %(dried by vacuum heating)"]], "name": "1-butyl-2-methylpyridinium bis((trifluoromethyl)sulfonyl)amide"}], "constr": [], "ref": {"full": "Bittner, B.; Wrobel, R. J.; Milchert, E. (2012) J. Chem. Thermodyn. 55, 159-165.", "title": "Physical properties of pyridinium ionic liquids"}, "title": "Transport properties: Viscosity", "expmeth": "Capillary tube (Ostwald; Ubbelohde) method", "solvent": null, "footer": ""}