{"phases": ["Liquid"], "dhead": [["Temperature, K", null], ["Pressure, kPa", null], ["Heat capacity at constant pressure, J/K/mol", "Liquid"]], "data": [[["296.2"], ["101.325"], ["383", "6.7"]], [["300.2"], ["101.325"], ["387.7", "6.7"]], [["304.2"], ["101.325"], ["392", "6.7"]], [["308.2"], ["101.325"], ["395.4", "6.9"]], [["312.2"], ["101.325"], ["398.9", "6.9"]], [["316.2"], ["101.325"], ["401.9", "6.9"]], [["320.2"], ["101.325"], ["404.1", "6.9"]], [["324.2"], ["101.325"], ["407", "6.9"]], [["328.2"], ["101.325"], ["410.4", "7.1"]], [["332.2"], ["101.325"], ["414.1", "7.1"]], [["336.2"], ["101.325"], ["417.9", "7.1"]], [["340.2"], ["101.325"], ["421.8", "7.1"]], [["344.2"], ["101.325"], ["425.8", "7.1"]], [["348.2"], ["101.325"], ["429.7", "7.3"]], [["352.2"], ["101.325"], ["433.9", "7.3"]], [["356.2"], ["101.325"], ["437.6", "7.3"]], [["360.2"], ["101.325"], ["442.5", "7.5"]], [["364.2"], ["101.325"], ["447.3", "7.5"]], [["368.2"], ["101.325"], ["452.2", "7.5"]], [["372.2"], ["101.325"], ["457.3", "7.5"]]], "components": [{"idout": "AAlxnT", "sample": [["Source:", "commercial source"], ["Purification:", "NMR (proton)"], ["Purity:", "0.98 mol %"], ["Purity analysis:", "none used"]], "name": "1-butyl-3-methylimidazolium thiocyanate", "formula": "C<SUB>9</SUB>H<SUB>15</SUB>N<SUB>3</SUB>S", "mw": "197.30"}], "constr": [], "footer": "", "expmeth": "Small sample (50 mg) scanning calorimetry", "solvent": null, "title": "Heat capacity and derived properties: Heat capacity at constant pressure", "ref": {"title": "Thermal Properties of Cyano-Based Ionic Liquids", "full": "Navarro, P.; Larriba, M.; Rojo, E.; Garcia, J.; Rodriguez, F. (2013) J. Chem. Eng. Data 58(8), 2187-2193."}}