{"components": [{"formula": "C<SUB>11</SUB>H<SUB>19</SUB>F<SUB>3</SUB>N<SUB>2</SUB>O<SUB>3</SUB>S", "idout": "ABIrWp", "sample": [["Source:", "commercial source"], ["Initial purification:", "stated by supplier"], ["Initial purity:", "99 mol %"], ["Final purification:", "Karl Fischer titration"], ["Final purity:", "0.02 water mass %(dried in a desiccator)"]], "name": "1-hexyl-3-methylimidazolium trifluoromethanesulfonate", "mw": "316.34"}], "constr": [], "phases": ["Liquid"], "dhead": [["Temperature, K", null], ["Pressure, kPa", null], ["Heat capacity at constant pressure, J/K/mol", "Liquid"]], "data": [[["283.15"], ["101.325"], ["484", "39"]], [["293.15"], ["101.325"], ["493", "40"]], [["303.15"], ["101.325"], ["500", "41"]], [["313.15"], ["101.325"], ["506", "41"]], [["323.15"], ["101.325"], ["513", "42"]], [["333.15"], ["101.325"], ["516", "42"]], [["343.15"], ["101.325"], ["522", "42"]]], "footer": "", "expmeth": "Small sample (50 mg) scanning calorimetry", "solvent": null, "ref": {"full": "Ficke, L. E.; Novak, R.; Brennecke, J. F. (2010) J. Chem. Eng. Data 55(11), 4946-4950.", "title": "Thermodynamic and Thermophysical Properties of Ionic Liquid + Water Systems"}, "title": "Heat capacity and derived properties: Heat capacity at constant pressure"}