{"footer": "", "expmeth": "Small sample (50 mg) scanning calorimetry", "solvent": null, "ref": {"full": "Mahrova, M.; Vilas, M.; Dominguez, A.; Gomez, E.; Calvar, N.; Tojo, E. (2012) J. Chem. Eng. Data 57(2), 241-248.", "title": "Physicochemical Characterization of New Sulfonate and Sulfate  Ammonium Ionic Liquids"}, "title": "Heat capacity and derived properties: Heat capacity at constant pressure", "constr": [], "components": [{"mw": "255.37", "idout": "AAxFKl", "sample": [["Source:", "synthesized by the authors"], ["Initial purification:", "estimated by the compiler"], ["Initial purity:", "98 mol %"], ["Final purification:", "Karl Fischer titration"], ["Final purity:", "0.00004 water mass %"]], "name": "N-ethyl-N,N-dimethyl-N-butylammonium ethyl sulfate", "formula": "C<SUB>10</SUB>H<SUB>25</SUB>NO<SUB>4</SUB>S"}], "phases": ["Liquid"], "dhead": [["Temperature, K", null], ["Pressure, kPa", null], ["Heat capacity at constant pressure, J/K/mol", "Liquid"]], "data": [[["360.15"], ["101.325"], ["451", "10"]], [["365.15"], ["101.325"], ["467", "10"]], [["370.15"], ["101.325"], ["478", "10"]], [["375.15"], ["101.325"], ["485", "11"]], [["380.15"], ["101.325"], ["491", "11"]], [["385.15"], ["101.325"], ["496", "11"]], [["390.15"], ["101.325"], ["500", "11"]]]}