{"constr": [], "components": [{"mw": "497.47", "sample": [["Source:", "synthesized by the authors"], ["Purification:", "estimated by the compiler"], ["Purity:", "98 mass %(dried by vacuum heating)"]], "idout": "ABrieg", "name": "3-cyano-1-octylpyridinium 1,1,1-trifluoro-N-[(trifluoromethyl)sulfonyl]methanesulfonamide", "formula": "C<SUB>16</SUB>H<SUB>21</SUB>F<SUB>6</SUB>N<SUB>3</SUB>O<SUB>4</SUB>S<SUB>2</SUB>"}], "dhead": [["Temperature, K", null], ["Pressure, kPa", null], ["Heat capacity at constant pressure, J/K/mol", "Liquid"]], "phases": ["Liquid"], "data": [[["298.15"], ["101.325"], ["709", "72"]], [["323.15"], ["101.325"], ["721", "73"]], [["353.15"], ["101.325"], ["731", "74"]]], "expmeth": "Small sample (50 mg) scanning calorimetry", "solvent": null, "footer": "", "title": "Heat capacity and derived properties: Heat capacity at constant pressure", "ref": {"title": "Synthesis, physical, and thermodynamic properties of 1-alkyl-cyanopyridinium  bis{(trifluoromethyl)sulfonyl}imide ionic liquids", "full": "Domanska, U.; Skiba, K.; Zawadzki, M.; Paduszynski, K.; Krolikowski, M. (2013) J. Chem. Thermodyn. 56, 153-161."}}