{"ref": {"full": "Crosthwaite, J. M.; Muldoon, M. J.; Dixon, J. K.; Anderson, J. L.; Brennecke, J. F. (2005) J. Chem. Thermodyn. 37(6), 559-568.", "title": "Phase transition and decomposition temperatures, heat capacities and viscosities of pyridinium ionic liquids"}, "title": "Heat capacity and derived properties: Heat capacity at constant pressure", "solvent": null, "expmeth": "Large sample (1 g) scanning calorimetry", "footer": "", "constr": [], "components": [{"mw": "458.43", "name": "1-hexyl-3-methylpyridinium 1,1,1-trifluoro-N-[(trifluoromethyl)sulfonyl]methanesulfonamide", "sample": [["Source:", "synthesized by the authors"], ["Purification:", "Karl Fischer titration"], ["Purity:", "0.0152 water mass %(dried by vacuum heating)"]], "idout": "ABkIKi", "formula": "C<SUB>14</SUB>H<SUB>20</SUB>F<SUB>6</SUB>N<SUB>2</SUB>O<SUB>4</SUB>S<SUB>2</SUB>"}], "data": [[["298"], ["101.325"], ["624", "63"]], [["323"], ["101.325"], ["644", "65"]]], "dhead": [["Temperature, K", null], ["Pressure, kPa", null], ["Heat capacity at constant pressure, J/K/mol", "Liquid"]], "phases": ["Liquid"]}