{"expmeth":"Vibrating tube method","data":[[["293.15"],["101.325"],["1241.9","1.3"]],[["303.15"],["101.325"],["1235.1","1.3"]],[["313.15"],["101.325"],["1228.3","1.3"]],[["323.15"],["101.325"],["1221.5","1.2"]],[["333.15"],["101.325"],["1214.8","1.2"]],[["343.15"],["101.325"],["1208.2","1.2"]],[["353.15"],["101.325"],["1201.6","1.2"]]],"phases":["Liquid"],"ref":{"title":"Thermophysical Properties of 1-Ethyl-3-methylimidazolium 1,1,2,2-Tetrafluoroethanesulfonate and 1-Ethyl-3-methylimidazolium Ethylsulfate Ionic Liquids as a Function of Temperature  ","full":"Larriba, M.; Garcia, S.; Garcia, J.; Torrecilla, J. S.; Rodriguez, F. (2011) J. Chem. Eng. Data 56(9), 3589-3597."},"title":"Volumetric properties: Specific density","dhead":[["Temperature, K",null],["Pressure, kPa",null],["Specific density, kg/m<SUP>3</SUP>","Liquid"]],"components":[{"idout":"AAtWdw","sample":[["Source:","commercial source"],["Initial purification:","stated by supplier"],["Initial purity:","99 mass %"],["Final purification:","gas chromatography;gas chromatography"],["Final purity:","0.0001 water mass %;0.0001 water mass %"]],"mw":"236.29","formula":"C<SUB>8</SUB>H<SUB>16</SUB>N<SUB>2</SUB>O<SUB>4</SUB>S","name":"1-ethyl-3-methylimidazolium ethyl sulfate"}],"constr":[],"footer":"","solvent":null}