{"phases":["Liquid"],"ref":{"full":"Singh, M.; Mandal, S.; Verma, Y.; Gupta, A.; Singh, R.; Chandra, S. (2014) J. Chem. Eng. Data 59(8), 2349-2359.","title":"Viscoelastic, Surface, and Volumetric Properties of Ionic Liquids [BMIM][OcSO4], [BMIM][PF6] and [EMIM][MeSO3]"},"expmeth":"Pycnometric method","data":[[["303"],["101.325"],["1247","14"]],[["308"],["101.325"],["1243","14"]],[["313"],["101.325"],["1240","14"]],[["318"],["101.325"],["1238","14"]],[["323"],["101.325"],["1234","14"]],[["328"],["101.325"],["1232","14"]],[["333"],["101.325"],["1230","14"]]],"solvent":null,"footer":"","title":"Volumetric properties: Specific density","components":[{"idout":"AAnigb","name":"1-ethyl-3-methylimidazolium methanesulfonate","sample":[["Source:","commercial source"],["Initial purification:","stated by supplier"],["Initial purity:","95 mass %"],["Final purification:","Karl Fischer titration;ion-selective electrode"],["Final purity:","0.5 water mass %;2 halide impurity mass %(dried in a desiccator;dried by vacuum heating)"]],"mw":"206.26","formula":"C<SUB>7</SUB>H<SUB>14</SUB>N<SUB>2</SUB>O<SUB>3</SUB>S"}],"dhead":[["Temperature, K",null],["Pressure, kPa",null],["Specific density, kg/m<SUP>3</SUP>","Liquid"]],"constr":[]}