{"title":"Volumetric properties: Specific density","dhead":[["Temperature, K",null],["Pressure, kPa",null],["Specific density, kg/m<SUP>3</SUP>","Liquid"]],"constr":[],"components":[{"sample":[["Source:","commercial source"],["Initial purification:","stated by supplier"],["Initial purity:","99.5 mol %"],["Final purification:","Karl Fischer titration"],["Final purity:","0.0015 water mass %(dried by vacuum heating)"]],"mw":"587.27","formula":"C<SUB>15</SUB>H<SUB>20</SUB>F<SUB>18</SUB>NP","name":"1-butyl-1-methylpyrrolidinium tris(pentafluoroethyl)trifluorophosphate","idout":"ACIwBp"}],"solvent":null,"footer":"","expmeth":"Vibrating tube method","data":[[["293.17"],["5000"],["1607","16"]],[["293.17"],["10000"],["1610","16"]],[["293.17"],["15000"],["1614","16"]],[["293.17"],["20000"],["1618","16"]],[["293.17"],["25000"],["1622","16"]],[["293.17"],["25000"],["1622","16"]],[["293.18"],["2500"],["1605","16"]],[["293.19"],["100"],["1604","16"]],[["293.19"],["500"],["1604","16"]],[["293.19"],["1000"],["1604","16"]],[["303.18"],["100"],["1593","16"]],[["303.19"],["1000"],["1593","16"]],[["303.2"],["500"],["1593","16"]],[["303.25"],["10000"],["1600","16"]],[["303.25"],["20000"],["1608","16"]],[["303.25"],["25000"],["1611","16"]],[["303.26"],["2500"],["1594","16"]],[["303.26"],["5000"],["1596","16"]],[["303.26"],["15000"],["1604","16"]],[["313.19"],["10000"],["1589","16"]],[["313.2"],["100"],["1582","16"]],[["313.2"],["500"],["1582","16"]],[["313.2"],["1000"],["1582","16"]],[["313.2"],["5000"],["1585","16"]],[["313.2"],["20000"],["1597","16"]],[["313.21"],["2500"],["1583","16"]],[["313.21"],["15000"],["1593","16"]],[["313.21"],["25000"],["1601","16"]],[["323.14"],["100"],["1571","16"]],[["323.14"],["500"],["1571","16"]],[["323.14"],["2500"],["1572","16"]],[["323.14"],["10000"],["1578","16"]],[["323.14"],["15000"],["1583","16"]],[["323.14"],["20000"],["1587","16"]],[["323.14"],["25000"],["1591","16"]],[["323.15"],["1000"],["1572","16"]],[["323.15"],["5000"],["1575","16"]],[["333.17"],["100"],["1560","16"]],[["333.17"],["500"],["1561","16"]],[["333.17"],["1000"],["1561","16"]],[["333.17"],["5000"],["1564","16"]],[["333.18"],["2500"],["1562","16"]],[["333.18"],["10000"],["1568","16"]],[["333.18"],["15000"],["1573","16"]],[["333.18"],["20000"],["1577","16"]],[["333.18"],["25000"],["1581","16"]],[["343.16"],["100"],["1550","16"]],[["343.17"],["500"],["1550","16"]],[["343.18"],["1000"],["1550","16"]],[["343.19"],["2500"],["1552","16"]],[["343.2"],["5000"],["1554","16"]],[["343.2"],["10000"],["1558","16"]],[["343.2"],["15000"],["1563","16"]],[["343.2"],["20000"],["1567","16"]],[["343.21"],["25000"],["1572","16"]],[["353.17"],["100"],["1540","15"]],[["353.17"],["500"],["1540","15"]],[["353.17"],["5000"],["1544","15"]],[["353.18"],["1000"],["1540","15"]],[["353.18"],["2500"],["1541","15"]],[["353.18"],["15000"],["1553","16"]],[["353.19"],["10000"],["1548","16"]],[["353.19"],["20000"],["1558","16"]],[["353.19"],["25000"],["1562","16"]]],"phases":["Liquid"],"ref":{"full":"Stevanovic, S.; Costa Gomes, M. F. (2013) J. Chem. Thermodyn. 59, 65-71.","title":"Solubility of carbon dioxide, nitrous oxide, ethane, and nitrogen in  1-butyl-1-methylpyrrolidinium and trihexyl(tetradecyl)phosphonium  tris(pentafluoroethyl)trifluorophosphate (eFAP) ionic liquids"}}