{"dhead":[["Temperature, K",null],["Pressure, kPa",null],["Specific density, kg/m<SUP>3</SUP>","Liquid"]],"constr":[],"components":[{"idout":"AAquyJ","name":"1-butylpyridinium tetrafluoroborate","sample":[["Source:","synthesized by others"],["Purification:","Karl Fischer titration;spectroscopy"],["Purity:","0.67 water mass %;0.001 halide impurity mass %(de-gassed by evacuation)"]],"mw":"223.02","formula":"C<SUB>9</SUB>H<SUB>14</SUB>BF<SUB>4</SUB>N"}],"title":"Volumetric properties: Specific density","solvent":null,"footer":"","data":[[["298.2"],["101.325"],["1214.4","8.6"]],[["303.2"],["101.325"],["1211.8","8.6"]],[["313.2"],["101.325"],["1205.3","8.6"]],[["323.2"],["101.325"],["1198.8","8.6"]],[["333.2"],["101.325"],["1192.2","8.6"]],[["343.2"],["101.325"],["1185.6","8.6"]]],"expmeth":"Pycnometric method","phases":["Liquid"],"ref":{"title":"Volume Expansivities and Isothermal Compressibilities of Imidazolium and Pyridinium-Based Ionic Liquids","full":"Gu, Z.; Brennecke, J. F. (2002) J. Chem. Eng. Data 47, 339-345."}}