{"title":"Volumetric properties: Specific density","components":[{"idout":"AApAUM","mw":"213.28","sample":[["Source:","synthesized by the authors"],["Purification:","NMR (proton)"],["Purity:","99 mol %(dried by vacuum heating)"]],"formula":"C<SUB>10</SUB>H<SUB>19</SUB>N<SUB>3</SUB>O<SUB>2</SUB>","name":"1-butyl-3-methylimidazolium glycinate"}],"dhead":[["Temperature, K",null],["Pressure, kPa",null],["Specific density, kg/m<SUP>3</SUP>","Liquid"]],"constr":[],"solvent":null,"footer":"","data":[[["298.15"],["101.325"],["1128.5","8"]],[["303.15"],["101.325"],["1125.9","8"]],[["313.15"],["101.325"],["1119.3","8"]],[["323.15"],["101.325"],["1112.8","8"]],[["333.15"],["101.325"],["1107.1","8"]],[["343.15"],["101.325"],["1100.5","8"]]],"expmeth":"Vibrating tube method","phases":["Liquid"],"ref":{"title":"Effect of Substituent Groups in Anions on Some Physicochemical Properties of 1-Butyl-3-methylimidazolium Carboxylate Ionic Liquids","full":"Xu, A.; Zhang, Y.; Li, Z.; Wang, J. (2013) J. Chem. Eng. Data 58(9), 2496-2501."}}