{"expmeth":"Pycnometric method","data":[[["298.15"],["101.325"],["1185","2"]],[["323.15"],["101.325"],["1171","2"]],[["348.15"],["101.325"],["1154","2"]],[["373.15"],["101.325"],["1144","2"]]],"phases":["Liquid"],"ref":{"full":"Shiflett, M. B.; Elliott, B. A.; Yokozeki, A. (2012) Fluid Phase Equilib. 316, 147-155.","title":"Phase behavior of vinyl fluoride in room-temperature ionic liquids [emim][Tf2N], [bmim][N(CN)2], [bmpy][BF4], [bmim][HFPS] and [omim][TFES]"},"components":[{"name":"1-butyl-4-methylpyridinium tetrafluoroborate","formula":"C<SUB>10</SUB>H<SUB>16</SUB>BF<SUB>4</SUB>N","sample":[["Source:","commercial source"],["Initial purification:","stated by supplier"],["Initial purity:","99 mass %"],["Final purification:","Karl Fischer titration"],["Final purity:","0.05 water mass %(dried by vacuum heating)"]],"mw":"237.05","idout":"AAtejP"}],"dhead":[["Temperature, K",null],["Pressure, kPa",null],["Specific density, kg/m<SUP>3</SUP>","Liquid"]],"constr":[],"title":"Volumetric properties: Specific density","footer":"","solvent":null}