{"solvent":null,"footer":"","dhead":[["Temperature, K",null],["Pressure, kPa",null],["Specific density, kg/m<SUP>3</SUP>","Liquid"]],"components":[{"idout":"AAtWdw","formula":"C<SUB>8</SUB>H<SUB>16</SUB>N<SUB>2</SUB>O<SUB>4</SUB>S","sample":[["Source:","synthesized by the authors"],["Purification:","Karl Fischer titration"],["Purity:","0.05 water mass %(de-gassed by evacuation;dried by oven heating)"]],"mw":"236.29","name":"1-ethyl-3-methylimidazolium ethyl sulfate"}],"constr":[],"title":"Volumetric properties: Specific density","ref":{"full":"Gonzalez, E. J.; Gonzales, B.; Calvar, N.; Dominguez, A. (2007) J. Chem. Eng. Data 52, 1641-1648.","title":"Physical Properties of Binary Mixtures of the Ionic Liquid 1-Ethyl-3-methylimidazolium Ethyl Sulfate with Several Alcohols at T = (298.15, 313.15, and 328.15) K and Atmospheric Pressure"},"phases":["Liquid"],"data":[[["298.15"],["101"],["1237.6","9.2"]],[["313.15"],["101"],["1227.5","9"]],[["328.15"],["101"],["1217.5","8.9"]]],"expmeth":"Vibrating tube method"}