{"expmeth":"Vibrating tube method","data":[[["313.15"],["101"],["1005.1","2.1"]],[["328.15"],["101"],["996.8","2.1"]]],"ref":{"full":"Gonzalez, E. J.; Gonzalez, B.; Macedo, E. A. (2013) J. Chem. Eng. Data 58(6), 1440-1448.","title":"Thermophysical Properties of the Pure Ionic Liquid 1-Butyl-1-methylpyrrolidinium Dicyanamide and Its Binary Mixtures with Alcohols"},"phases":["Liquid"],"components":[{"idout":"AAoDZh","name":"1-butyl-1-methylpyrrolidinium dicyanamide","mw":"208.30","sample":[["Source:","commercial source"],["Initial purification:","stated by supplier"],["Initial purity:","98 mass %"],["Final purification:","Karl Fischer titration"],["Final purity:","0.15 water mass %"]],"formula":"C<SUB>11</SUB>H<SUB>20</SUB>N<SUB>4</SUB>"}],"dhead":[["Temperature, K",null],["Pressure, kPa",null],["Specific density, kg/m<SUP>3</SUP>","Liquid"]],"constr":[],"title":"Volumetric properties: Specific density","footer":"","solvent":null}