{"ref":{"full":"Fareghi-Alamdari, R.; Hatefipour, R. (2015) Thermochim. Acta 617, 172-178.","title":"Synthesis and thermophysical characterization of novel azide functionalized imidazolium based ionic liquids"},"phases":["Liquid"],"data":[[["298"],["101.325"],["1560","20"]]],"expmeth":"Pycnometric method","footer":"","solvent":null,"constr":[],"dhead":[["Temperature, K",null],["Pressure, kPa",null],["Specific density, kg/m<SUP>3</SUP>","Liquid"]],"components":[{"mw":"419.12","sample":[["Source:","synthesized by the authors"],["Purity analysis:","dried by vacuum heating;solvent extraction"]],"formula":"C<SUB>12</SUB>H<SUB>17</SUB>Br<SUB>2</SUB>N<SUB>7</SUB>","name":"3-(2-azido-3-(1-methyl-1H-imidazol-3-ium-3-yl)propyl)-1-vinyl-1H-imidazol-3-ium dibromide","idout":"ABcfPp"}],"title":"Volumetric properties: Specific density"}