{"solvent":null,"footer":"","components":[{"idout":"ADWghx","sample":[["Source:","commercial source"],["Initial purification:","stated by supplier"],["Initial purity:","98 mass %"],["Final purification:","Karl Fischer titration"],["Final purity:","0.0016 water mass %(dried by vacuum heating)"]],"formula":"C<SUB>38</SUB>H<SUB>68</SUB>F<SUB>18</SUB>P<SUB>2</SUB>","mw":"928.87","name":"trihexyl(tetradecyl)phosphonium tris(pentafluoroethyl)trifluorophosphate"}],"dhead":[["Temperature, K",null],["Pressure, kPa",null],["Specific density, kg/m<SUP>3</SUP>","Liquid"]],"constr":[],"title":"Volumetric properties: Specific density","phases":["Liquid"],"ref":{"title":"Influence of Molecular Structure on Densities and Viscosities of Several Ionic Liquids","full":"Gacino, F. M.; Regueira, T.; Lugo, L.; Comunas, M. J. P.; Fernandez, J. (2011) J. Chem. Eng. Data 56(12), 4984-4999."},"data":[[["268.15"],["101.325"],["1207.4","1.5"]],[["273.15"],["101.325"],["1203.2","1.5"]],[["278.15"],["101.325"],["1198.9","1.5"]],[["283.15"],["101.325"],["1194.6","1.5"]],[["288.15"],["101.325"],["1190.3","1.5"]],[["293.15"],["101.325"],["1186","1.5"]],[["298.15"],["101.325"],["1181.7","1.5"]],[["303.15"],["101.325"],["1177.6","1.5"]],[["308.15"],["101.325"],["1173.5","1.5"]],[["313.15"],["101.325"],["1169.4","1.5"]],[["318.15"],["101.325"],["1165.3","1.5"]],[["323.15"],["101.325"],["1161.3","1.5"]],[["328.15"],["101.325"],["1157.3","1.5"]],[["333.15"],["101.325"],["1153.3","1.5"]],[["338.15"],["101.325"],["1149.3","1.5"]],[["343.15"],["101.325"],["1145.3","1.4"]],[["348.15"],["101.325"],["1141.2","1.4"]],[["353.15"],["101.325"],["1137","1.4"]],[["358.15"],["101.325"],["1132.7","1.4"]],[["363.15"],["101.325"],["1128.7","1.4"]],[["368.15"],["101.325"],["1124.9","1.4"]],[["373.15"],["101.325"],["1121.1","1.4"]]],"expmeth":"Vibrating tube method"}