{"ref":{"title":"Thermodynamic properties of aqueous solutions of two ammonium-based protic ionic liquids at 298.15 K","full":"Hou, M.; Xu, Y.; Han, Y.; Chen, B.; Zhang, W.; Ye, Q.; Sun, J. (2013) J. Mol. Liq. 178, 149-155."},"phases":["Liquid"],"expmeth":"Vibrating tube method","data":[[["298.15"],["101"],["1017.71","0.81"]]],"solvent":null,"footer":"","dhead":[["Temperature, K",null],["Pressure, kPa",null],["Specific density, kg/m<SUP>3</SUP>","Liquid"]],"components":[{"idout":"AAULBQ","mw":"105.14","sample":[["Source:","synthesized by the authors"],["Purification:","estimated by the compiler;Karl Fischer titration"],["Purity:","99 mol %;0.018 water mass %"]],"formula":"C<SUB>4</SUB>H<SUB>11</SUB>NO<SUB>2</SUB>","name":"ethylammonium acetate"}],"constr":[],"title":"Volumetric properties: Specific density"}