{"data":[[["301.15"],["101.325"],["1274","4"]]],"expmeth":"Pycnometric method","phases":["Liquid"],"ref":{"title":"Solubility and Diffusivity of Difluoromethane in Room-Temperature Ionic Liquids","full":"Shiflett, M. B.; Harmer, M. A.; Junk, C. P.; Yokozeki, A. (2006) J. Chem. Eng. Data 51(2), 483-495."},"dhead":[["Temperature, K",null],["Pressure, kPa",null],["Specific density, kg/m<SUP>3</SUP>","Liquid"]],"constr":[],"components":[{"idout":"ABRjvH","mw":"362.38","sample":[["Source:","synthesized by the authors"],["Purification:","Karl Fischer titration"],["Purity:","0.03 water mass %"]],"formula":"C<SUB>13</SUB>H<SUB>22</SUB>F<SUB>4</SUB>N<SUB>2</SUB>O<SUB>3</SUB>S","name":"1-heptyl-3-methylimidazolium 1,1,2,2-tetrafluoroethanesulfonate"}],"title":"Volumetric properties: Specific density","footer":"","solvent":null}