{"constr":[],"dhead":[["Temperature, K",null],["Pressure, kPa",null],["Specific density, kg/m<SUP>3</SUP>","Liquid"]],"components":[{"name":"1-ethyl-3-methylimidazolium thiocyanate","sample":[["Source:","commercial source"],["Initial purification:","stated by supplier"],["Initial purity:","98 mass %"],["Final purification:","Karl Fischer titration"],["Final purity:","0.03 water mass %(dried by vacuum heating)"]],"formula":"C<SUB>7</SUB>H<SUB>11</SUB>N<SUB>3</SUB>S","mw":"169.25","idout":"AAgcbj"}],"title":"Volumetric properties: Specific density","footer":"","solvent":null,"expmeth":"Vibrating tube method","data":[[["278.15"],["101.325"],["1129.7","1.4"]],[["283.15"],["101.325"],["1126.5","1.4"]],[["288.15"],["101.325"],["1123.3","1.4"]],[["293.15"],["101.325"],["1120.1","1.4"]],[["298.15"],["101.325"],["1117","1.4"]],[["303.15"],["101.325"],["1113.9","1.4"]],[["308.15"],["101.325"],["1110.8","1.4"]],[["313.15"],["101.325"],["1107.8","1.4"]],[["318.15"],["101.325"],["1104.8","1.4"]],[["323.15"],["101.325"],["1101.8","1.4"]],[["328.15"],["101.325"],["1098.8","1.4"]],[["333.15"],["101.325"],["1095.9","1.4"]],[["338.15"],["101.325"],["1093","1.4"]],[["343.15"],["101.325"],["1090.1","1.4"]],[["348.15"],["101.325"],["1087.2","1.4"]],[["353.15"],["101.325"],["1084.3","1.4"]],[["358.15"],["101.325"],["1081.5","1.4"]],[["363.15"],["101.325"],["1078.7","1.4"]]],"phases":["Liquid"],"ref":{"full":"Neves, C. M. S. S.; Kurnia, K. A.; Coutinho, J. A. P.; Marrucho, I. M.; Lopes, J. N. C.; Freire, M. G.; Rebelo, L. P. N. (2013) J. Phys. Chem. B 117, 10271-10283.","title":"Systematic Study of the Thermophysical Properties of Imidazolium- Based Ionic Liquids with Cyano-Functionalized Anions"}}