{"ref":{"title":"Thermophysical properties of sulfonium- and ammonium-based ionic liquids","full":"Bhattacharjee, A.; Luis, A.; Lopes-da-Silva, J. A.; Freire, M. G.; Carvalho, P. J.; Coutinho, J. A. P. (2014) Fluid Phase Equilib. 381, 36-45."},"phases":["Liquid"],"data":[[["283.15"],["101.325"],["1477","1.2"]],[["288.15"],["101.325"],["1472","1.2"]],[["293.15"],["101.325"],["1467.1","1.2"]],[["298.15"],["101.325"],["1462.1","1.2"]],[["303.15"],["101.325"],["1457.3","1.2"]],[["308.15"],["101.325"],["1452.4","1.2"]],[["313.15"],["101.325"],["1447.6","1.2"]],[["318.15"],["101.325"],["1442.8","1.2"]],[["323.15"],["101.325"],["1438.1","1.1"]],[["328.15"],["101.325"],["1433.4","1.1"]],[["333.15"],["101.325"],["1428.7","1.1"]],[["338.15"],["101.325"],["1424","1.1"]],[["343.15"],["101.325"],["1419.4","1.1"]],[["348.15"],["101.325"],["1414.8","1.1"]],[["353.15"],["101.325"],["1410.2","1.1"]]],"expmeth":"Vibrating tube method","solvent":null,"footer":"","constr":[],"dhead":[["Temperature, K",null],["Pressure, kPa",null],["Specific density, kg/m<SUP>3</SUP>","Liquid"]],"components":[{"name":"triethylsulfonium bis((trifluoromethyl)sulfonyl)imide","sample":[["Source:","commercial source"],["Initial purification:","stated by supplier"],["Initial purity:","99 mass %"],["Final purification:","Karl Fischer titration"],["Final purity:","0.0463 water mass %(dried by vacuum heating)"]],"mw":"399.39","formula":"C<SUB>8</SUB>H<SUB>15</SUB>F<SUB>6</SUB>NO<SUB>4</SUB>S<SUB>3</SUB>","idout":"ABYphX"}],"title":"Volumetric properties: Specific density"}