{"title":"Volumetric properties: Specific density","constr":[],"dhead":[["Temperature, K",null],["Pressure, kPa",null],["Specific density, kg/m<SUP>3</SUP>","Liquid"]],"components":[{"name":"tributylethylphosphonium diethylphosphate","sample":[["Source:","commercial source"],["Initial purification:","stated by supplier"],["Initial purity:","99 mass %"],["Final purification:","Karl Fischer titration"],["Final purity:","0.079 water mass %(dried by vacuum heating)"]],"mw":"384.47","formula":"C<SUB>18</SUB>H<SUB>42</SUB>O<SUB>4</SUB>P<SUB>2</SUB>","idout":"ABVwRj"}],"solvent":null,"footer":"","expmeth":"Vibrating tube method","data":[[["298.15"],["101.325"],["996","10"]],[["303.15"],["101.325"],["993","10"]],[["308.15"],["101.325"],["989","10"]],[["313.15"],["101.325"],["986","10"]],[["318.15"],["101.325"],["982","10"]],[["323.15"],["101.325"],["979","10"]],[["328.15"],["101.325"],["975","10"]],[["333.15"],["101.325"],["972","10"]],[["338.15"],["101.325"],["968","10"]],[["343.15"],["101.325"],["965","10"]],[["348.15"],["101.325"],["961","10"]],[["353.15"],["101.325"],["958","10"]],[["358.15"],["101.325"],["954","10"]],[["363.15"],["101.325"],["950","10"]],[["368.15"],["101.325"],["947","10"]]],"phases":["Liquid"],"ref":{"full":"Krolikowska, M.; Orawiec, M. (2016) J. Chem. Eng. Data 61(5), 1793-1802.","title":"Activity Coefficients at Infinite Dilution of Organic Solutes and Water in Tributylethylphosphonium Diethylphosphate Using Gas Liquid Chromatography: Thermodynamic Properties of Mixtures Containing Ionic Liquids"}}