{"solvent":null,"footer":"","dhead":[["Temperature, K",null],["Pressure, kPa",null],["Specific density, kg/m<SUP>3</SUP>","Liquid"]],"constr":[],"components":[{"idout":"ABdMlD","name":"1-methyl-1-propylpiperidinium bis(trifluoromethylsulfonyl)imide","sample":[["Source:","commercial source"],["Initial purification:","stated by supplier"],["Initial purity:","99 mass %"],["Final purification:","Karl Fischer titration;NMR (proton)"],["Final purity:","0.0098 water mass %;99 mass %(dried by vacuum heating)"]],"mw":"422.41","formula":"C<SUB>11</SUB>H<SUB>20</SUB>F<SUB>6</SUB>N<SUB>2</SUB>O<SUB>4</SUB>S<SUB>2</SUB>"}],"title":"Volumetric properties: Specific density","ref":{"full":"Bhattacharjee, A.; Carvalho, P. J.; Coutinho, J. A. P. (2014) Fluid Phase Equilib. 375, 80-88.","title":"The effect of the cation aromaticity upon the thermophysical properties of piperidinium- and pyridinium-based Ionic Liquids"},"phases":["Liquid"],"expmeth":"Vibrating tube method","data":[[["288.15"],["101.325"],["1420.3","1.1"]],[["293.15"],["101.325"],["1415.8","1.1"]],[["298.15"],["101.325"],["1411.4","1.1"]],[["303.15"],["101.325"],["1407","1.1"]],[["308.15"],["101.325"],["1402.6","1.1"]],[["313.15"],["101.325"],["1398.2","1.1"]],[["318.15"],["101.325"],["1393.9","1.1"]],[["323.15"],["101.325"],["1389.6","1.1"]],[["328.15"],["101.325"],["1385.3","1.1"]],[["333.15"],["101.325"],["1381","1.1"]],[["338.15"],["101.325"],["1376.7","1.1"]],[["343.15"],["101.325"],["1372.5","1.1"]],[["348.15"],["101.325"],["1368.3","1.1"]],[["353.15"],["101.325"],["1364.1","1.1"]]]}