{"data":[[["293.15"],["101.325"],["1128.9","9.2"]],[["295.16"],["101.325"],["1128.2","9.2"]],[["298.15"],["101.325"],["1127.6","9.2"]],[["303.09"],["101.325"],["1126.8","9.2"]],[["308.13"],["101.325"],["1126.1","9.2"]],[["313.17"],["101.325"],["1124.5","9.2"]],[["318.16"],["101.325"],["1123.6","9.2"]],[["323.11"],["101.325"],["1122.1","9.2"]],[["328.14"],["101.325"],["1119.7","9.1"]],[["330.09"],["101.325"],["1118.3","9.1"]],[["333.16"],["101.325"],["1116.2","9.1"]],[["335.05"],["101.325"],["1114.4","9.1"]],[["338.14"],["101.325"],["1110.5","9"]]],"expmeth":"Pycnometric method","ref":{"full":"Hou, H.-Y.; Huang, Y.; Wang, S.; Bai, B. (2011) Acta Phys. Chim. Sin. 27(11), 2512-2520.","title":"Preparation and Physicochemical Properties of Imidazolium Acetates and the Conductivities of Their Aqueous and Ethanol Solutions"},"phases":["Liquid"],"title":"Volumetric properties: Specific density","dhead":[["Temperature, K",null],["Pressure, kPa",null],["Specific density, kg/m<SUP>3</SUP>","Liquid"]],"components":[{"name":"1,3-dimethylimidazolium acetate","sample":[["Source:","synthesized by the authors"],["Purity analysis:","dried by vacuum heating"]],"formula":"C<SUB>7</SUB>H<SUB>12</SUB>N<SUB>2</SUB>O<SUB>2</SUB>","mw":"156.18","idout":"AAeBiP"}],"constr":[],"footer":"","solvent":null}