{"footer":"","solvent":null,"components":[{"sample":[["Source:","synthesized by the authors"],["Purification:","NMR (proton);chemical analysis"],["Purity:","99 mass %;0.005 halide impurity mass %(de-gassed by evacuation)"]],"formula":"C<SUB>6</SUB>H<SUB>11</SUB>BF<SUB>4</SUB>N<SUB>2</SUB>","mw":"197.97","name":"1-ethyl-3-methylimidazolium tetrafluoroborate","idout":"AAmDhG"}],"dhead":[["Temperature, K",null],["Pressure, kPa",null],["Specific density, kg/m<SUP>3</SUP>","Liquid"]],"constr":[],"title":"Volumetric properties: Specific density","ref":{"title":"Density and Viscosity Data for Mixtures of Ionic Liquids with a Common Anion","full":"Song, D.; Chen, J. (2014) J. Chem. Eng. Data 59(2), 257-262."},"phases":["Liquid"],"expmeth":"Vibrating tube method","data":[[["293.15"],["101.325"],["1283.9","1.1"]],[["298.15"],["101.325"],["1280","1.1"]],[["303.15"],["101.325"],["1276.2","1.1"]],[["308.15"],["101.325"],["1272.4","1.1"]],[["313.15"],["101.325"],["1268.6","1.1"]],[["318.15"],["101.325"],["1264.9","1.1"]],[["323.15"],["101.325"],["1261.2","1.1"]],[["328.15"],["101.325"],["1257.4","1.1"]],[["333.15"],["101.325"],["1253.8","1.1"]],[["338.15"],["101.325"],["1250.1","1.1"]],[["343.15"],["101.325"],["1246.5","1.1"]]]}