{"solvent":null,"footer":"","title":"Volumetric properties: Specific density","dhead":[["Temperature, K",null],["Pressure, kPa",null],["Specific density, kg/m<SUP>3</SUP>","Liquid"]],"constr":[],"components":[{"mw":"226.32","sample":[["Source:","synthesized by the authors"],["Purification:","estimated by the compiler"],["Purity:","99 mass %(dried by vacuum heating)"]],"formula":"C<SUB>12</SUB>H<SUB>22</SUB>N<SUB>2</SUB>O<SUB>2</SUB>","name":"1-methyl-3-pentylimidazolium propanoate","idout":"AArbqK"}],"phases":["Liquid"],"ref":{"full":"Hong, M.; Sun, A.; Liu, C.; Guan, W.; Tong, J.; Yang, J. -Z. (2013) Ind. Eng. Chem. Res. 52, 15679-15683.","title":"Physico-chemical Properties of 1.Alkyl-3-methylimidazolium Propionate Ionic Liquids {[Cnmim][Pro](n = 3, 4, 5, 6)} from 288.15 K to 328.15 K"},"expmeth":"Vibrating tube method","data":[[["288.15"],["101"],["1026.95","0.32"]],[["293.15"],["101"],["1023.89","0.32"]],[["298.15"],["101"],["1020.51","0.32"]],[["303.15"],["101"],["1017.68","0.31"]],[["308.15"],["101"],["1014.71","0.31"]],[["313.15"],["101"],["1011.75","0.31"]],[["318.15"],["101"],["1008.72","0.31"]],[["323.15"],["101"],["1005.72","0.3"]],[["328.15"],["101"],["1002.69","0.3"]]]}