{"data":[[["278.15"],["101.325"],["1310.1","4.2"]],[["283.15"],["101.325"],["1306","4.2"]],[["288.15"],["101.325"],["1301.9","4.2"]],[["293.15"],["101.325"],["1297.9","4.2"]],[["298.15"],["101.325"],["1293.7","4.1"]],[["303.15"],["101.325"],["1289.6","4.1"]],[["308.15"],["101.325"],["1285.4","4.1"]],[["313.15"],["101.325"],["1281.3","4.1"]],[["318.15"],["101.325"],["1277.2","4.1"]]],"expmeth":"Vibrating tube method","ref":{"title":"Properties of ionic liquid HMIMPF6 with carbonates, ketones and alkyl acetates","full":"Pereiro, A. B.; Tojo, E.; Rodriguez, A.; Canosa, J.; Tojo, J. (2006) J. Chem. Thermodyn. 38, 651-661."},"phases":["Liquid"],"dhead":[["Temperature, K",null],["Pressure, kPa",null],["Specific density, kg/m<SUP>3</SUP>","Liquid"]],"components":[{"idout":"ABICUs","sample":[["Source:","synthesized by the authors"]],"mw":"312.24","formula":"C<SUB>10</SUB>H<SUB>19</SUB>F<SUB>6</SUB>N<SUB>2</SUB>P","name":"1-hexyl-3-methylimidazolium hexafluorophosphate"}],"constr":[],"title":"Volumetric properties: Specific density","solvent":null,"footer":""}