{"phases":["Liquid"],"ref":{"title":"A Computational and Experimental Study of the Heat Transfer Properties of Nine Different Ionic Liquids","full":"Tenney, C. M.; Massel, M.; Mayes, J. M.; Sen, M.; Brennecke, J. F.; Maginn, E. J. (2014) J. Chem. Eng. Data 59(2), 391-399."},"expmeth":"Vibrating tube method","data":[[["283"],["101.325"],["1342.5","8.1"]],[["293"],["101.325"],["1333.7","8"]],[["303"],["101.325"],["1325.1","8"]],[["313"],["101.325"],["1316.5","7.9"]],[["323"],["101.325"],["1308","7.9"]],[["333"],["101.325"],["1299.5","7.8"]],[["343"],["101.325"],["1291","7.8"]],[["353"],["101.325"],["1282.5","7.7"]],[["363"],["101.325"],["1274.2","7.7"]]],"solvent":null,"footer":"","title":"Volumetric properties: Specific density","constr":[],"dhead":[["Temperature, K",null],["Pressure, kPa",null],["Specific density, kg/m<SUP>3</SUP>","Liquid"]],"components":[{"formula":"C<SUB>16</SUB>H<SUB>25</SUB>F<SUB>6</SUB>N<SUB>3</SUB>O<SUB>4</SUB>S<SUB>2</SUB>","sample":[["Source:","synthesized by the authors"],["Purification:","not known;Karl Fischer titration"],["Purity:","99 mass %;0.000031 water mass %(dried by vacuum heating)"]],"mw":"501.51","name":"1-hexyl-3-methyl-4-(dimethylamino)pyridinium 1,1,1-trifluoro-N-[(trifluoromethyl)sulfonyl]methanesulfonamide","idout":"ABsXru"}]}